mkdocs_pug
