Metadata-Version: 2.1
Name: mkdocs-pug
Version: 0.0.2
Summary: Pug plugin for mkdocs.
Home-page: https://github.com/vzhong/mkdocs_pug
Author: Victor Zhong
Author-email: victor@victorzhong.com
License: Apache 2
Keywords: text nlp machine-learning
Platform: UNKNOWN
Classifier: Development Status :: 3 - Alpha
Classifier: Intended Audience :: Developers
Classifier: License :: OSI Approved :: MIT License
Classifier: Programming Language :: Python :: 3
Requires-Python: >3.7
Provides-Extra: dev
Provides-Extra: test
